document_parse/__init__.py
document_parse/llamaparse.py
document_parse/main_file_s3_to_llamaparse.py
mcp_purchase/__init__.py
mcp_purchase/__main__.py
mcp_purchase/constants.py
mcp_purchase/databases.py
mcp_purchase/generate_mail_html.py
mcp_purchase/html_link_from_md.py
mcp_purchase/prompts.py
mcp_purchase/resources.py
mcp_purchase/server.py
mcp_purchase/tool_schema.py
mcp_purchase/tools.py
mcp_purchase/utils.py
mcp_purchase/Agent/main.py
mcp_purchase/Agent/markdown_logger.py
mcp_purchase/Agent/setup.py
mcp_purchase/Agent/app/__init__.py
mcp_purchase/Agent/app/bedrock.py
mcp_purchase/Agent/app/config.py
mcp_purchase/Agent/app/exceptions.py
mcp_purchase/Agent/app/llm.py
mcp_purchase/Agent/app/logger.py
mcp_purchase/Agent/app/schema.py
mcp_purchase/Agent/app/toolHandler.py
mcp_purchase/Agent/app/agent/__init__.py
mcp_purchase/Agent/app/agent/base.py
mcp_purchase/Agent/app/agent/casefileAgent.py
mcp_purchase/Agent/app/agent/react.py
mcp_purchase/Agent/app/agent/toolcall.py
mcp_purchase/Agent/app/sandbox/__init__.py
mcp_purchase/Agent/app/sandbox/client.py
mcp_purchase/Agent/app/sandbox/core/exceptions.py
mcp_purchase/Agent/app/sandbox/core/manager.py
mcp_purchase/Agent/app/sandbox/core/sandbox.py
mcp_purchase/Agent/app/sandbox/core/terminal.py
mcp_purchase/Agent/app/tool/__init__.py
mcp_purchase/Agent/app/tool/base.py
mcp_purchase/Agent/app/tool/create_chat_completion.py
mcp_purchase/Agent/app/tool/mcp_tool.py
mcp_purchase/Agent/app/tool/terminate.py
mcp_purchase/Agent/app/tool/tool_collection.py
mcp_purchase/Agent/app/tool/search/__init__.py
mcp_purchase/Agent/app/tool/search/baidu_search.py
mcp_purchase/Agent/app/tool/search/base.py
mcp_purchase/Agent/app/tool/search/bing_search.py
mcp_purchase/Agent/app/tool/search/duckduckgo_search.py
mcp_purchase/Agent/app/tool/search/google_search.py
mcp_purchase/Agent/app/tool/search/vessel_database_search.py
mcp_purchase/Agent/app/tool/search/vessel_search.py
mcp_purchase/Agent/config/config.toml
syia_mcp_purchase_2025_x7k9-0.1.18.dist-info/METADATA
syia_mcp_purchase_2025_x7k9-0.1.18.dist-info/WHEEL
syia_mcp_purchase_2025_x7k9-0.1.18.dist-info/top_level.txt
syia_mcp_purchase_2025_x7k9-0.1.18.dist-info/RECORD
